localproxy/__init__.py
localproxy/cli.py
localproxy/proxy.py
pylocalproxy-0.1.0.dist-info/LICENSE
pylocalproxy-0.1.0.dist-info/METADATA
pylocalproxy-0.1.0.dist-info/WHEEL
pylocalproxy-0.1.0.dist-info/entry_points.txt
pylocalproxy-0.1.0.dist-info/RECORD
